{
  "generated_at": "2026-03-10",
  "source": "static public demo artifacts",
  "boundary_outcomes": {
    "low": {
      "decision_id": "DEC-2026-03-04-LOW-001",
      "decision_version": 1,
      "risk_tier": "low",
      "decision_state": "committed",
      "governance_verdict": "allow",
      "commit_allowed": true,
      "review_required": false
    },
    "high": {
      "decision_id": "DEC-2026-03-05-001",
      "decision_version": 1,
      "risk_tier": "high",
      "reason_code": "high_risk_action_requires_review",
      "decision_state": "committed",
      "governance_verdict": "review_required",
      "commit_allowed": true,
      "review_required": true
    },
    "critical": {
      "decision_id": "DEC-2026-03-05-900",
      "decision_version": 1,
      "risk_tier": "critical",
      "reason_code": "external_write_without_required_controls",
      "decision_state": "rejected",
      "governance_verdict": "block",
      "commit_allowed": false,
      "review_required": false
    }
  },
  "governance_model": {
    "persisted_decision_states": [
      "committed",
      "rejected"
    ],
    "review_workflow": "separate_from_decision_lifecycle",
    "immutability_rule": "new_data_creates_new_decision_version"
  }
}
